nosem/__init__.py
nosem/interpreter.py
nosem/main.py
nosem/project.py
nosem/targets.py
nosem-0.0.2.dist-info/LICENSE
nosem-0.0.2.dist-info/METADATA
nosem-0.0.2.dist-info/WHEEL
nosem-0.0.2.dist-info/entry_points.txt
nosem-0.0.2.dist-info/top_level.txt
nosem-0.0.2.dist-info/RECORD
