Metadata-Version: 2.1
Name: nosem
Version: 0.0.2
Summary: Python binding to meson build system
Home-page: https://github.com/Garcia6l20/nosem
Author: Sylvain Garcia
Author-email: garcia.6l20@gmail.com
License: MIT
Keywords: nosem,meson,build system,cmake
Platform: UNKNOWN
Classifier: Development Status :: 1 - Planning
Classifier: Environment :: Console
Classifier: Intended Audience :: Developers
Classifier: License :: OSI Approved :: MIT License
Classifier: Natural Language :: English
Classifier: Operating System :: MacOS :: MacOS X
Classifier: Operating System :: Microsoft :: Windows
Classifier: Operating System :: POSIX :: BSD
Classifier: Operating System :: POSIX :: Linux
Classifier: Programming Language :: Python :: 3 :: Only
Classifier: Programming Language :: Python :: 3.8
Classifier: Programming Language :: Python :: 3.9
Classifier: Topic :: Software Development :: Build Tools
Requires-Python: >=3.8
License-File: LICENSE
Requires-Dist: requests
Requires-Dist: meson ; python_version >= "0.58"
